ibm_gdsc_sdk_saas/__init__.py
ibm_gdsc_sdk_saas/api_client.py
ibm_gdsc_sdk_saas/api_response.py
ibm_gdsc_sdk_saas/configuration.py
ibm_gdsc_sdk_saas/exceptions.py
ibm_gdsc_sdk_saas/py.typed
ibm_gdsc_sdk_saas/rest.py
ibm_gdsc_sdk_saas/api/__init__.py
ibm_gdsc_sdk_saas/api/assets_service_api.py
ibm_gdsc_sdk_saas/api/audit_service_api.py
ibm_gdsc_sdk_saas/api/auth_server_service_api.py
ibm_gdsc_sdk_saas/api/cloud_accounts_api.py
ibm_gdsc_sdk_saas/api/compliance_accelerator_api.py
ibm_gdsc_sdk_saas/api/connections_service_api.py
ibm_gdsc_sdk_saas/api/dashboards_service_api.py
ibm_gdsc_sdk_saas/api/data_movements_api.py
ibm_gdsc_sdk_saas/api/data_resources_api.py
ibm_gdsc_sdk_saas/api/data_sensitivities_api.py
ibm_gdsc_sdk_saas/api/data_stores_api.py
ibm_gdsc_sdk_saas/api/data_vulnerabilities_api.py
ibm_gdsc_sdk_saas/api/databootstrapper_service_api.py
ibm_gdsc_sdk_saas/api/datamart_processor_service_api.py
ibm_gdsc_sdk_saas/api/ecosystem_service_api.py
ibm_gdsc_sdk_saas/api/feature_flags_service_api.py
ibm_gdsc_sdk_saas/api/group_builder_api.py
ibm_gdsc_sdk_saas/api/guardium_connector_api.py
ibm_gdsc_sdk_saas/api/health_collector_api.py
ibm_gdsc_sdk_saas/api/jumpbox_service_api.py
ibm_gdsc_sdk_saas/api/notifications_service_api.py
ibm_gdsc_sdk_saas/api/outliers_engine_api.py
ibm_gdsc_sdk_saas/api/pipelineconfig_service_api.py
ibm_gdsc_sdk_saas/api/policy_builder_api.py
ibm_gdsc_sdk_saas/api/qs_data_loader_api.py
ibm_gdsc_sdk_saas/api/qs_data_manager_api.py
ibm_gdsc_sdk_saas/api/qs_plugin_manager_api.py
ibm_gdsc_sdk_saas/api/qs_policy_manager_api.py
ibm_gdsc_sdk_saas/api/reports_runner_api.py
ibm_gdsc_sdk_saas/api/reports_service_api.py
ibm_gdsc_sdk_saas/api/risk_analytics_controller_api.py
ibm_gdsc_sdk_saas/api/risk_analytics_data_processor_api.py
ibm_gdsc_sdk_saas/api/risk_analytics_engine_api.py
ibm_gdsc_sdk_saas/api/risk_analytics_ml_classification_api.py
ibm_gdsc_sdk_saas/api/scheduler_service_api.py
ibm_gdsc_sdk_saas/api/snif_assist_service_api.py
ibm_gdsc_sdk_saas-3.0.20250703.dist-info/METADATA
ibm_gdsc_sdk_saas-3.0.20250703.dist-info/WHEEL
ibm_gdsc_sdk_saas-3.0.20250703.dist-info/top_level.txt
ibm_gdsc_sdk_saas-3.0.20250703.dist-info/RECORD
